Workbook

Sheet Cover
B1: LBO Model - Smartsheet Inc.
B3: Table of Contents
B5: {=RIGHT(CELL("filename",A1),LEN(CELL("filename",A1))-FIND("]",CELL("filename",A1)))} -> Cover
B6: {=RIGHT(CELL("filename",Outputs!A1),LEN(CELL("filename",Outputs!A1))-FIND("]",CELL("filename",Outputs!A1)))} -> Outputs
B7: {=RIGHT(CELL("filename",'Transaction Assumptions'!A2),LEN(CELL("filename",'Transaction Assumptions'!A2))-FIND("]",CELL("filename",'Transaction Assumptions'!A2)))} -> Transaction Assumptions
B8: {=RIGHT(CELL("filename",'Forecasting Assumptions'!A3),LEN(CELL("filename",'Forecasting Assumptions'!A3))-FIND("]",CELL("filename",'Forecasting Assumptions'!A3)))} -> Forecasting Assumptions
B9: {=RIGHT(CELL("filename",Model!A4),LEN(CELL("filename",Model!A4))-FIND("]",CELL("filename",Model!A4)))} -> Model
B11: Form 10-K
B13: Income Statement
B14: Balance Sheet
B15: Statement of Cash Flows
B17: Model Circularity
B19: Model Circularity | D19: 2 | S19: Circularity
S20: On
S21: Off
B23: =IF($D$19=1,"This model now has the circularity turned on. Please confirm the Excel settings below","")
B24: =IF($D$19=1,"PC","") | C24: =IF($D$19=1,"File - Options - Formulas - Check the box on the top-right labeled 'Enable iterative calculation'.","")
B25: =IF($D$19=1,"Mac","") | C25: =IF($D$19=1,"Excel - Preferences - Calculation - Check the box near the bottom labeled 'Use iterative calculation'.","")

Sheet Outputs
C1: Performance & Returns Analysis
C3: Purchase Price | H3: Sources and Uses of Cash
C5: Equity Offer Value | H5: Sources of Cash | N5: Uses of Cash
C6: Enterprise Value | F6: ='Transaction Assumptions'!C17 -> 6086597.7 | H6: Cash (Target) | L6: ='Transaction Assumptions'!J8 -> 428795 | N6: Equity Offer Value | Q6: ='Transaction Assumptions'!N8 -> 6715392.7
C7: Less: Debt | F7: =-'Transaction Assumptions'!C15 -> 0 | H7: Revolving Credit Line | L7: ='Transaction Assumptions'!J12 -> 0 | N7: Refinance Debt | Q7: ='Transaction Assumptions'!N9 -> 0
C8: Plus: Cash Balance | F8: =-'Transaction Assumptions'!C16 -> 628795 | H8: Term Loan A | L8: ='Transaction Assumptions'!J9 -> 540831.42 | N8: Closing Costs | Q8: ='Transaction Assumptions'!N10 -> 45000
C9: Equity Offer Value | F9: =SUM(F6:F8) -> 6715392.7 | H9: Subordinated Debt | L9: ='Transaction Assumptions'!J10 -> 1487286.4 | N9: Total Uses of Cash | Q9: =SUM(Q6:Q8) -> 6760392.7
H10: Sponsor Equity | L10: ='Transaction Assumptions'!J11 -> 4303479.9
H11: Total Sources of Cash | L11: =SUM(L6:L10) -> 6760392.7
C12: US$/Share | F12: ='Transaction Assumptions'!C8 -> 42.66
C13: Premium (Discount) | F13: ='Transaction Assumptions'!C9 -> 0.15 | Q13: All figures in USD thousands
C15: Forecast Financial Performance
C16: =Model!$B$6 -> Model Running: Base Case Drivers
D18: Sponsor Investment | I18: Sponsor Equity IRR 1 | O18: Sponsor Cash-on-Cash 1 | T18: Jeff: I added Sponsor Invesment here. Please check.
T19: So they can see how much of their capital is earning the IRR shown.
D20: ='Transaction Assumptions'!J11/1000000 -> 4.3034799 | I20: =Model!$E$400 -> 0.26933178 | O20: =Model!$F$400 -> 4.1881138
Q22: IRR and Cash-on-Cash returns assume a 6-year horizon.
C24: EBITDA Growth & Debt Paydown | K24: Credit Metrics & Debt Covenants (Year 2030 - Target Covenants) | W24: =Model!K5 -> 2025 | X24: =Model!L5 -> 2026 | Y24: =Model!M5 -> 2027 | Z24: =Model!N5 -> 2028 | AA24: =Model!O5 -> 2029 | AB24: =Model!P5 -> 2030 | AC24: =Model!Q5 -> 2031 | AD24: =Model!R5 -> 2032 | ... AF24: =Model!T5 -> 2034
T26: Revenue | W26: =Model!K8 -> 1245839.4 | X26: =Model!L8 -> 1619591.2 | Y26: =Model!M8 -> 2105468.6 | Z26: =Model!N8 -> 2716054.5 | AA26: =Model!O8 -> 3503710.3 | AB26: =Model!P8 -> 4460223.2 | AC26: =Model!Q8 -> 5468233.6 | AD26: =Model!R8 -> 6441579.2 | ... AF26: =Model!T8 -> 7897401.9
T27: EBITDA | W27: =Model!K17 -> 31145.985 | X27: =Model!L17 -> 129567.3 | Y27: =Model!M17 -> 231601.54 | Z27: =Model!N17 -> 407408.17 | AA27: =Model!O17 -> 630667.85 | AB27: =Model!P17 -> 981249.1 | AC27: =Model!Q17 -> 1312376.1 | AD27: =Model!R17 -> 1545979 | ... AF27: =Model!T17 -> 1974350.5
T28: Total Debt | W28: =Model!K289 -> 2002277.5 | X28: =Model!L289 -> 2122168.8 | Y28: =Model!M289 -> 2198282.9 | Z28: =Model!N289 -> 2175071 | AA28: =Model!O289 -> 2135192 | AB28: =Model!P289 -> 2188571.8 | AC28: =Model!Q289 -> 2243286.1 | AD28: =Model!R289 -> 2299368.2 | ... AF28: =Model!T289 -> 2415773.7
T30: Total Debt / EBITDA Covenant 1: max 4,0x by 2030 | W30: =Model!K349 -> 64.286858 | X30: =Model!L349 -> 16.378892 | Y30: =Model!M349 -> 9.4916589 | Z30: =Model!N349 -> 5.3388006 | AA30: =Model!O349 -> 3.3856046 | AB30: =Model!P349 -> 2.2303937 | AC30: =Model!Q349 -> 1.7093317 | AD30: =Model!R349 -> 1.4873218 | ... AF30: =Model!T349 -> 1.223579
T31: Debt Service Coverage Ratio Covenant 2: min. 2,0x by 2030 | W31: =Model!K361 -> 0.026331939 | X31: =Model!L361 -> 0.39987564 | Y31: =Model!M361 -> 0.74770364 | Z31: =Model!N361 -> 1.3463686 | AA31: =Model!O361 -> 2.1015586 | AB31: =Model!P361 -> 3.6168762 | AC31: =Model!Q361 -> 4.7196777 | AD31: =Model!R361 -> 6.0208492 | ... AF31: =Model!T361 -> 11.20944
C42: Returns Analysis
C43: =$C$16 -> Model Running: Base Case Drivers
C45: Return Attribution ($ millions) | K45: Equity Investor Returns by Investment Horizon
T47: Return Attribution | V47: Entry | W47: Exit | X47: Change | AA47: Equity Investor | AB47: IRR | AC47: Cash-on-Cash | AG47: Chart Options
T48: Beginning Equity | U48: ='Transaction Assumptions'!J11 -> 4303479.9 | AA48: =Model!D405 -> 1 | AB48: =Model!E405 -> NA | AC48: =Model!F405 -> -0.31935965
T49: Fees | U49: =-'Transaction Assumptions'!N10 -> -45000 | AA49: =Model!D404 -> 2 | AB49: =Model!E404 -> -0.66755822 | AC49: =Model!F404 -> 0.11018458 | AG49: TRUE
T50: EBITDA Growth | U50: =X50 -> 13538384 | V50: =Model!J8*W69 -> 6086597.7 | W50: =Model!P377*W70 -> 19624982 | X50: =+W50-V50 -> 13538384 | AA50: =Model!D403 -> 3 | AB50: =Model!E403 -> -0.17232965 | AC50: =Model!F403 -> 0.56669209
T51: Multiple Expansion | U51: =+X51*Y51 -> 0 | V51: ='Transaction Assumptions'!C28 -> 6.3512015 | W51: ='Transaction Assumptions'!C29 -> 6.3512015 | X51: =W51-V51 -> 0 | AA51: =Model!D402 -> 4 | AB51: =Model!E402 -> 0.085578629 | AC51: =Model!F402 -> 1.3891299 | AG51: Label Position
T52: Net Debt Paydown | U52: =+X52 -> 226599.13 | V52: =SUM('Transaction Assumptions'!$J$9:$J$10)-'Transaction Assumptions'!$J$27 -> 1828117.8 | W52: =Model!P384 -> 1601518.7 | X52: =+V52-W52 -> 226599.13 | AA52: =Model!D401 -> 5 | AB52: =Model!E401 -> 0.19806692 | AC52: =Model!F401 -> 2.4707877 | AG52: 2
T53: Ending Equity | U53: =SUM(U48:U52) -> 18023463 | AA53: =Model!D400 -> 6 | AB53: =Model!E400 -> 0.26933178 | AC53: =Model!F400 -> 4.1881138
AA54: =Model!D399 -> 7 | AB54: =Model!E399 -> 0.28736649 | AC54: =Model!F399 -> 5.8683567
T55: Ending Equity ≠ Model? | U55: =IF(ROUND(U53-Model!P389,3)=0,0,1) -> 0 | AA55: =Model!D398 -> 8 | AB55: =Model!E398 -> 0.27875568 | AC55: =Model!F398 -> 7.1595506 | AH55: Data | AI55: Base | AJ55: Before | AK55: After | AL55: Elev X | AM55: Elev Y | AN55: Middle Y | AO55: Above Y | AP55: Below Y | AQ55: Label
AA56: =Model!D397 -> 9 | AB56: =Model!E397 -> 0.2711315 | AC56: =Model!F397 -> 8.6810183 | AE56: =Outputs!T48 -> Beginning Equity | AH56: =Outputs!U48/1000 -> 4303.4799 | AI56: =IF(OR(LEN(AH56)=0,AND(ROW()=ROW($AF$56:$AF$61),Outputs!$AG$49)),AM56,"") -> 4303.4799 | AJ56: =IF(OR(LEN(AH56)=0,AND(ROW()=ROW($AF$56:$AF$61),Outputs!$AG$49),ROW()=ROW($AF$56:$AF$61)+ROWS($AL$56:$AL$61)-1),NA(),AM56-AH56) -> #N/A | AK56: =IF(OR(LEN(AH56)=0,AND(ROW()=ROW($AF$56:$AF$61),Outputs!$AG$49),ROW()=ROW($AF$56:$AF$61)+ROWS($AL$56:$AL$61)-1),NA(),AM56) -> #N/A | AL56: =IF(ROW()=ROW($AF$56:$AF$61),1.5,IF(ROW()=ROW($AF$56:$AF$61)+ROWS($AL$56:$AL$61)-1,NA(),OFFSET(AL56,-1,0)+1)) -> 1.5 | AM56: =IF(ROW()=ROW($AF$56:$AF$61),0,OFFSET(AM56,-1,0))+IF(LEN(AH56)>0,AH56,0) -> 4303.4799 | AN56: =IF(Outputs!$AG$52=1,IF(LEN(AI56)>0,AI56/2,AVERAGE(AJ56,AK56)),NA()) -> #N/A | AO56: =IF(OR(Outputs!$AG$52=3,AND(Outputs!$AG$52=2,OR(AND(LEN(AI56)>0,AM56>0),AND(LEN(AH56)>0,AH56>0)))),IF(LEN(AI56)>0,MAX(0,AM56),MAX(AJ56,AK56)),NA()) -> 4303.4799 | AP56: =IF(Outputs!$AG$52=2,IF(LEN(AI56)>0,IF(AI56<0,AI56,NA()),IF(LEN(AH56)>0,IF(AH56<0,MIN(AJ56,AK56),NA()),NA())),NA()) -> #N/A | AQ56: =IF(LEN(AH56)>0,AH56,AI56) -> 4303.4799
AA57: =Model!D396 -> 10 | AB57: =Model!E396 -> 0.25485952 | AC57: =Model!F396 -> 9.6997714 | AE57: =Outputs!T49 -> Fees | AH57: =Outputs!U49/1000 -> -45 | AI57: =IF(OR(LEN(AH57)=0,AND(ROW()=ROW($AF$56:$AF$61),Outputs!$AG$49)),AM57,"") | AJ57: =IF(OR(LEN(AH57)=0,AND(ROW()=ROW($AF$56:$AF$61),Outputs!$AG$49),ROW()=ROW($AF$56:$AF$61)+ROWS($AL$56:$AL$61)-1),NA(),AM57-AH57) -> 4303.4799 | AK57: =IF(OR(LEN(AH57)=0,AND(ROW()=ROW($AF$56:$AF$61),Outputs!$AG$49),ROW()=ROW($AF$56:$AF$61)+ROWS($AL$56:$AL$61)-1),NA(),AM57) -> 4258.4799 | AL57: =IF(ROW()=ROW($AF$56:$AF$61),1.5,IF(ROW()=ROW($AF$56:$AF$61)+ROWS($AL$56:$AL$61)-1,NA(),OFFSET(AL57,-1,0)+1)) -> 2.5 | AM57: =IF(ROW()=ROW($AF$56:$AF$61),0,OFFSET(AM57,-1,0))+IF(LEN(AH57)>0,AH57,0) -> 4258.4799 | AN57: =IF(Outputs!$AG$52=1,IF(LEN(AI57)>0,AI57/2,AVERAGE(AJ57,AK57)),NA()) -> #N/A | AO57: =IF(OR(Outputs!$AG$52=3,AND(Outputs!$AG$52=2,OR(AND(LEN(AI57)>0,AM57>0),AND(LEN(AH57)>0,AH57>0)))),IF(LEN(AI57)>0,MAX(0,AM57),MAX(AJ57,AK57)),NA()) -> #N/A | AP57: =IF(Outputs!$AG$52=2,IF(LEN(AI57)>0,IF(AI57<0,AI57,NA()),IF(LEN(AH57)>0,IF(AH57<0,MIN(AJ57,AK57),NA()),NA())),NA()) -> 4258.4799 | AQ57: =IF(LEN(AH57)>0,AH57,AI57) -> -45
AE58: =Outputs!T50 -> EBITDA Growth | AH58: =Outputs!U50/1000 -> 13538.384 | AI58: =IF(OR(LEN(AH58)=0,AND(ROW()=ROW($AF$56:$AF$61),Outputs!$AG$49)),AM58,"") | AJ58: =IF(OR(LEN(AH58)=0,AND(ROW()=ROW($AF$56:$AF$61),Outputs!$AG$49),ROW()=ROW($AF$56:$AF$61)+ROWS($AL$56:$AL$61)-1),NA(),AM58-AH58) -> 4258.4799 | AK58: =IF(OR(LEN(AH58)=0,AND(ROW()=ROW($AF$56:$AF$61),Outputs!$AG$49),ROW()=ROW($AF$56:$AF$61)+ROWS($AL$56:$AL$61)-1),NA(),AM58) -> 17796.864 | AL58: =IF(ROW()=ROW($AF$56:$AF$61),1.5,IF(ROW()=ROW($AF$56:$AF$61)+ROWS($AL$56:$AL$61)-1,NA(),OFFSET(AL58,-1,0)+1)) -> 3.5 | AM58: =IF(ROW()=ROW($AF$56:$AF$61),0,OFFSET(AM58,-1,0))+IF(LEN(AH58)>0,AH58,0) -> 17796.864 | AN58: =IF(Outputs!$AG$52=1,IF(LEN(AI58)>0,AI58/2,AVERAGE(AJ58,AK58)),NA()) -> #N/A | AO58: =IF(OR(Outputs!$AG$52=3,AND(Outputs!$AG$52=2,OR(AND(LEN(AI58)>0,AM58>0),AND(LEN(AH58)>0,AH58>0)))),IF(LEN(AI58)>0,MAX(0,AM58),MAX(AJ58,AK58)),NA()) -> 17796.864 | AP58: =IF(Outputs!$AG$52=2,IF(LEN(AI58)>0,IF(AI58<0,AI58,NA()),IF(LEN(AH58)>0,IF(AH58<0,MIN(AJ58,AK58),NA()),NA())),NA()) -> #N/A | AQ58: =IF(LEN(AH58)>0,AH58,AI58) -> 13538.384
AE59: =Outputs!T51 -> Multiple Expansion | AH59: =Outputs!U51/1000 -> 0 | AI59: =IF(OR(LEN(AH59)=0,AND(ROW()=ROW($AF$56:$AF$61),Outputs!$AG$49)),AM59,"") | AJ59: =IF(OR(LEN(AH59)=0,AND(ROW()=ROW($AF$56:$AF$61),Outputs!$AG$49),ROW()=ROW($AF$56:$AF$61)+ROWS($AL$56:$AL$61)-1),NA(),AM59-AH59) -> 17796.864 | AK59: =IF(OR(LEN(AH59)=0,AND(ROW()=ROW($AF$56:$AF$61),Outputs!$AG$49),ROW()=ROW($AF$56:$AF$61)+ROWS($AL$56:$AL$61)-1),NA(),AM59) -> 17796.864 | AL59: =IF(ROW()=ROW($AF$56:$AF$61),1.5,IF(ROW()=ROW($AF$56:$AF$61)+ROWS($AL$56:$AL$61)-1,NA(),OFFSET(AL59,-1,0)+1)) -> 4.5 | AM59: =IF(ROW()=ROW($AF$56:$AF$61),0,OFFSET(AM59,-1,0))+IF(LEN(AH59)>0,AH59,0) -> 17796.864 | AN59: =IF(Outputs!$AG$52=1,IF(LEN(AI59)>0,AI59/2,AVERAGE(AJ59,AK59)),NA()) -> #N/A | AO59: =IF(OR(Outputs!$AG$52=3,AND(Outputs!$AG$52=2,OR(AND(LEN(AI59)>0,AM59>0),AND(LEN(AH59)>0,AH59>0)))),IF(LEN(AI59)>0,MAX(0,AM59),MAX(AJ59,AK59)),NA()) -> #N/A | AP59: =IF(Outputs!$AG$52=2,IF(LEN(AI59)>0,IF(AI59<0,AI59,NA()),IF(LEN(AH59)>0,IF(AH59<0,MIN(AJ59,AK59),NA()),NA())),NA()) -> #N/A | AQ59: =IF(LEN(AH59)>0,AH59,AI59) -> 0
AE60: =Outputs!T52 -> Net Debt Paydown | AH60: =Outputs!U52/1000 -> 226.59913 | AI60: =IF(OR(LEN(AH60)=0,AND(ROW()=ROW($AF$56:$AF$61),Outputs!$AG$49)),AM60,"") | AJ60: =IF(OR(LEN(AH60)=0,AND(ROW()=ROW($AF$56:$AF$61),Outputs!$AG$49),ROW()=ROW($AF$56:$AF$61)+ROWS($AL$56:$AL$61)-1),NA(),AM60-AH60) -> 17796.864 | AK60: =IF(OR(LEN(AH60)=0,AND(ROW()=ROW($AF$56:$AF$61),Outputs!$AG$49),ROW()=ROW($AF$56:$AF$61)+ROWS($AL$56:$AL$61)-1),NA(),AM60) -> 18023.463 | AL60: =IF(ROW()=ROW($AF$56:$AF$61),1.5,IF(ROW()=ROW($AF$56:$AF$61)+ROWS($AL$56:$AL$61)-1,NA(),OFFSET(AL60,-1,0)+1)) -> 5.5 | AM60: =IF(ROW()=ROW($AF$56:$AF$61),0,OFFSET(AM60,-1,0))+IF(LEN(AH60)>0,AH60,0) -> 18023.463 | AN60: =IF(Outputs!$AG$52=1,IF(LEN(AI60)>0,AI60/2,AVERAGE(AJ60,AK60)),NA()) -> #N/A | AO60: =IF(OR(Outputs!$AG$52=3,AND(Outputs!$AG$52=2,OR(AND(LEN(AI60)>0,AM60>0),AND(LEN(AH60)>0,AH60>0)))),IF(LEN(AI60)>0,MAX(0,AM60),MAX(AJ60,AK60)),NA()) -> 18023.463 | AP60: =IF(Outputs!$AG$52=2,IF(LEN(AI60)>0,IF(AI60<0,AI60,NA()),IF(LEN(AH60)>0,IF(AH60<0,MIN(AJ60,AK60),NA()),NA())),NA()) -> #N/A | AQ60: =IF(LEN(AH60)>0,AH60,AI60) -> 226.59913
AE61: =Outputs!T53 -> Ending Equity | AI61: =IF(OR(LEN(AF61)=0,AND(ROW()=ROW($AF$56:$AF$61),Outputs!$AG$49)),AM61,"") -> 18023.463 | AJ61: =IF(OR(LEN(AF61)=0,AND(ROW()=ROW($AF$56:$AF$61),Outputs!$AG$49),ROW()=ROW($AF$56:$AF$61)+ROWS($AL$56:$AL$61)-1),NA(),AM61-AF61) -> #N/A | AK61: =IF(OR(LEN(AF61)=0,AND(ROW()=ROW($AF$56:$AF$61),Outputs!$AG$49),ROW()=ROW($AF$56:$AF$61)+ROWS($AL$56:$AL$61)-1),NA(),AM61) -> #N/A | AL61: =IF(ROW()=ROW($AF$56:$AF$61),1.5,IF(ROW()=ROW($AF$56:$AF$61)+ROWS($AL$56:$AL$61)-1,NA(),OFFSET(AL61,-1,0)+1)) -> #N/A | AM61: =IF(ROW()=ROW($AF$56:$AF$61),0,OFFSET(AM61,-1,0))+IF(LEN(AF61)>0,AF61,0) -> 18023.463 | AN61: =IF(Outputs!$AG$52=1,IF(LEN(AI61)>0,AI61/2,AVERAGE(AJ61,AK61)),NA()) -> #N/A | AO61: =IF(OR(Outputs!$AG$52=3,AND(Outputs!$AG$52=2,OR(AND(LEN(AI61)>0,AM61>0),AND(LEN(AF61)>0,AF61>0)))),IF(LEN(AI61)>0,MAX(0,AM61),MAX(AJ61,AK61)),NA()) -> 18023.463 | AP61: =IF(Outputs!$AG$52=2,IF(LEN(AI61)>0,IF(AI61<0,AI61,NA()),IF(LEN(AF61)>0,IF(AF61<0,MIN(AJ61,AK61),NA()),NA())),NA()) -> #N/A | AQ61: =IF(LEN(AF61)>0,AF61,AI61) -> 18023.463
C63: Sensitivity Analysis
C65: Sponsor IRR (Entry vs Exit Multiple) | K65: Sponsor Cash-on-Cash (Entry vs Exit Multiple)
C66: Entry EV / EBITDA | D66: Entry EV / Sales | E66: Exit EV / EBITDA | K66: Entry EV / EBITDA | L66: Entry EV / Sales | M66: Exit EV / EBITDA
D67: =$I$20 -> 0.26933178 | E67: =F67-0.5 -> 19 | F67: =G67-0.5 -> 19.5 | G67: ='Transaction Assumptions'!C31 -> 20 | H67: =+G67+0.5 -> 20.5 | I67: =+H67+0.5 -> 21 | L67: =$O$20 -> 4.1881138 | M67: =E67 -> 19 | N67: =F67 -> 19.5 | O67: =G67 -> 20 | P67: =H67 -> 20.5 | Q67: =I67 -> 21 | T67: Sensitivity Inputs
C68: 19 | D68: =D69-0.5 -> 5.3512015 | E68: 0.29910263 | F68: 0.30510216 | G68: 0.31096674 | H68: 0.31670286 | I68: 0.32231657 | K68: 19 | L68: =D68 -> 5.3512015 | M68: 4.8137495 | N68: 4.9488094 | O68: 5.0838693 | P68: 5.2189293 | Q68: 5.3539892
C69: 19.5 | D69: =D70-0.5 -> 5.8512015 | E69: 0.27743134 | F69: 0.28340537 | G69: 0.28924337 | H69: 0.29495197 | I69: 0.30053731 | K69: 19.5 | L69: =D69 -> 5.8512015 | M69: 4.3511901 | N69: 4.4748335 | O69: 4.5984769 | P69: 4.7221203 | Q69: 4.8457637 | T69: Entry EV/Sales | W69: ='Transaction Assumptions'!C28 -> 6.3512015
C70: 20 | D70: ='Transaction Assumptions'!C28 -> 6.3512015 | E70: 0.2575545 | F70: 0.26351182 | G70: 0.26933178 | H70: 0.27502117 | I70: 0.28058624 | K70: 20 | L70: =D70 -> 6.3512015 | M70: 3.9601008 | N70: 4.0741073 | O70: 4.1881138 | P70: 4.3021202 | Q70: 4.4161267 | T70: Exit EV/EBITDA | W70: 20
C71: 20.5 | D71: =+D70+0.5 -> 6.8512015 | E71: 0.23918975 | F71: 0.24513771 | G71: 0.25094677 | H71: 0.25662385 | I71: 0.26217539 | K71: 20.5 | L71: =D71 -> 6.8512015 | M71: 3.6252438 | N71: 3.731007 | O71: 3.8367702 | P71: 3.9425333 | Q71: 4.0482965
C72: 21 | D72: =+D71+0.5 -> 7.3512015 | E72: 0.22212302 | F72: 0.22806768 | G72: 0.2338717 | H72: 0.23954219 | I72: 0.24508575 | K72: 21 | L72: =D72 -> 7.3512015 | M72: 3.3355457 | N72: 3.4341773 | O72: 3.5328088 | P72: 3.6314404 | Q72: 3.7300719

Sheet Transaction Assumptions
B1: Transaction Structure
B3: Purchase Price | E3: Sources & Uses
B5: All figures in USD thousands unless stated
B7: Equity Offer Value | E7: Sources of Cash | J7: Amount | L7: Uses of Cash | N7: Amount
B8: US$/Share H2-2024 | C8: 42.66 | E8: Cash on hand (+Short-term inv) | I8: =J8/J13 -> 0.063427528 | J8: =-C16-J27 -> 428795 | L8: Equity Offer Value | N8: =C25 -> 6715392.7
B9: Premium | C9: 0.15 | E9: Senior Secured Term Loan A | I9: 0.08 | J9: =I9*J13 -> 540831.42 | L9: Refinance LT Debt | N9: 0
B10: Shares Outstanding | C10: 136884011 | E10: Subordinated Debt / Mezzanine | I10: 0.22 | J10: =I10*J13 -> 1487286.4 | L10: Transaction Fees | N10: 45000
B11: Equity Offer Value | C11: =C8*(1+C9)*C10/1000 -> 6715392.7 | E11: Sponsor Equity | I11: =70%-I8 -> 0.63657247 | J11: =I11*J13 -> 4303479.9
E12: Revolving Credit Line, undrawn | I12: 0 | J12: 0
B13: Enterprise Value | E13: Total Sources | J13: =N13 -> 6760392.7 | L13: Total Uses | N13: =SUM(N8:N10) -> 6760392.7
B14: Equity Offer Value | C14: =C11 -> 6715392.7
B15: Plus: Long-term Debt | C15: 0
B16: Less: Cash + Short term bonds | C16: =-(BS!C4+BS!C5) -> -628795
B17: Enterprise Value | C17: =C14+C15+C16 -> 6086597.7
B19: Other Inputs
B21: From EV to Equity | E21: General Inputs
B22: 2024 Sales for Valuation | C22: =IS!D6 -> 958338 | E22: First Forecast Fiscal Year | I22: (YY-MM-DD) | J22: 45688
B23: Entry EV/Sales | C23: =Outputs!W69 -> 6.3512015 | E23: Transaction Close Date | I23: (YY-MM-DD) | J23: 45322
B24: Enterprise Value | C24: =C23*C22 -> 6086597.7 | E24: First Year of Forecast | I24: (Year) | J24: 2025
B25: Equity Offer Value | C25: =C24-SUM(C15:C16) -> 6715392.7 | E25: Days in Period | I25: (Days) | J25: 365
E26: Tax Rate | J26: 0.25
B27: EBITDA Multiples | E27: Start (Minimum) Cash Balance 2025 | J27: 200000
B28: Entry EV/Sales | C28: 6.3512015 | E28: Interest Rate on Deposits | J28: 0.035
B29: Exit EV/Sales | C29: 6.3512015 | E29: Dividends payments | J29: 0
B30: Entry EV/EBITDA | C30: 20
B31: Exit EV/EBITDA | C31: 20
B34: Debt Assumptions
B36: All figures in USD thousands
E37: Standby | F37: Floating | G37: Fixed
B38: Type | C38: Amount | D38: Limit | E38: Fee | F38: Coupon | G38: Coupon
B39: Revolving Credit Line | C39: =$J$12 -> 0 | D39: 300000 | E39: 0.005 | F39: 200 | G39: N/A
B40: Term Loan A | C40: =$J$9 -> 540831.42 | D40: N/A | E40: N/A | F40: 275 | G40: N/A
B41: Subordinated Debt | C41: =$J$10 -> 1487286.4 | D41: N/A | E41: N/A | F41: N/A | G41: 0.1
B42: Cash (Target) | C42: =J12 -> 0 | D42: N/A | E42: N/A | F42: N/A | G42: N/A
B43: Sponsor Equity | C43: =$J$11 -> 4303479.9 | D43: N/A | E43: N/A | F43: N/A | G43: N/A
B44: Total | C44: =SUM(C39:C43) -> 6331597.7
B46: Mandatory Principal Repayment | C46: Cash Sweep | D46: 1 | E46: =D46+1 -> 2 | F46: =E46+1 -> 3 | G46: =F46+1 -> 4 | H46: =G46+1 -> 5 | I46: =H46+1 -> 6 | J46: =I46+1 -> 7 | K46: =J46+1 -> 8 | L46: =K46+1 -> 9 | M46: =L46+1 -> 10
B47: Subordinated Debt | C47: N/A | D47: 0 | E47: 0 | F47: 0 | G47: 0 | H47: 0 | I47: 0 | J47: 0 | K47: 0 | L47: 0 | M47: 0
B48: Term Loan A | C48: 1 | D48: 0.1 | E48: 0.1 | F48: 0.1 | G48: 0.1 | H48: 0.1 | I48: 0.1 | J48: 0.1 | K48: 0.1 | L48: 0.1 | M48: 0.1
B50: PIK Rate Percentage | D50: 1 | E50: =D50+1 -> 2 | F50: =E50+1 -> 3 | G50: =F50+1 -> 4 | H50: =G50+1 -> 5 | I50: =H50+1 -> 6 | J50: =I50+1 -> 7 | K50: =J50+1 -> 8 | L50: =K50+1 -> 9 | M50: =L50+1 -> 10
B51: Subordinated Debt | D51: 0.75 | E51: 0.75 | F51: 0.75 | G51: 0.75 | H51: 0.75 | I51: 0.25 | J51: 0.25 | K51: 0.25 | L51: 0.25 | M51: 0.25
B53: Debt Covenants
B54: Targeted Year (Covenant to apply) | D54: 6
B55: Max. Total Debt / EBITDA | D55: 4
B56: Total Debt / EBITDA Reduction | D56: 0.5
B57: Min. Debt Service Coverage Ratio | D57: 2
N59: The Excess Cash Flow sweep represents the percentage of excess cash that can be allocated to discretionary debt paydowns.
N60: PIK rate represents the percentage of the Subordinated Debt Coupon that is paid-in-kind.

Sheet Forecasting Assumptions
B1: Financial Drivers & Scenarios
B3: Income Statement Drivers
B5: All figures in USD thousands unless stated | G5: 2025 | H5: =G5+1 -> 2026 | I5: =H5+1 -> 2027 | J5: =I5+1 -> 2028 | K5: =J5+1 -> 2029 | L5: =K5+1 -> 2030 | M5: =L5+1 -> 2031 | N5: =M5+1 -> 2032 | O5: =N5+1 -> 2033 | P5: =O5+1 -> 2034
B7: Driver Switch | E7: 2
B9: Revenue (% YoY growth) | G9: {=INDEX(G11:G13,$E$7)} -> 0.3 | H9: {=INDEX(H11:H13,$E$7)} -> 0.3 | I9: {=INDEX(I11:I13,$E$7)} -> 0.3 | J9: {=INDEX(J11:J13,$E$7)} -> 0.29 | K9: {=INDEX(K11:K13,$E$7)} -> 0.29 | L9: {=INDEX(L11:L13,$E$7)} -> 0.273 | M9: {=INDEX(M11:M13,$E$7)} -> 0.226 | N9: {=INDEX(N11:N13,$E$7)} -> 0.178 | ... P9: {=INDEX(P11:P13,$E$7)} -> 0.084
B11: Best Case | G11: 0.32 | H11: 0.32 | I11: 0.32 | J11: 0.3 | K11: 0.3 | L11: 0.25 | M11: 0.25 | N11: 0.2 | O11: 0.15 | P11: 0.1
B12: Base Case | G12: 0.3 | H12: 0.3 | I12: 0.3 | J12: 0.29 | K12: 0.29 | L12: 0.273 | M12: 0.226 | N12: 0.178 | O12: 0.131 | P12: 0.084
B13: Worst Case | G13: 0.27 | H13: 0.27 | I13: 0.27 | J13: 0.26 | K13: 0.26 | L13: 0.24 | M13: 0.21 | N13: 0.16 | O13: 0.13 | P13: 0.07
B15: Gross margin (% of Revenue) | G15: {=INDEX(G17:G19,$E$7)} -> 0.81 | H15: {=INDEX(H17:H19,$E$7)} -> 0.81 | I15: {=INDEX(I17:I19,$E$7)} -> 0.81 | J15: {=INDEX(J17:J19,$E$7)} -> 0.81 | K15: {=INDEX(K17:K19,$E$7)} -> 0.81 | L15: {=INDEX(L17:L19,$E$7)} -> 0.81 | M15: {=INDEX(M17:M19,$E$7)} -> 0.81 | N15: {=INDEX(N17:N19,$E$7)} -> 0.81 | ... P15: {=INDEX(P17:P19,$E$7)} -> 0.81
B17: =$B$11 -> Best Case | G17: 0.825 | H17: 0.825 | I17: 0.825 | J17: 0.825 | K17: 0.825 | L17: 0.825 | M17: 0.825 | N17: 0.825 | O17: 0.825 | P17: 0.825
B18: =$B$12 -> Base Case | G18: 0.81 | H18: 0.81 | I18: 0.81 | J18: 0.81 | K18: 0.81 | L18: 0.81 | M18: 0.81 | N18: 0.81 | O18: 0.81 | P18: 0.81
B19: =$B$13 -> Worst Case | G19: 0.8 | H19: 0.8 | I19: 0.8 | J19: 0.8 | K19: 0.8 | L19: 0.8 | M19: 0.8 | N19: 0.8 | O19: 0.8 | P19: 0.8
B21: SG&A (% of Revenue) | G21: {=INDEX(G23:G25,$E$7)} -> 0.61 | H21: {=INDEX(H23:H25,$E$7)} -> 0.57 | I21: {=INDEX(I23:I25,$E$7)} -> 0.54 | J21: {=INDEX(J23:J25,$E$7)} -> 0.51 | K21: {=INDEX(K23:K25,$E$7)} -> 0.48 | L21: {=INDEX(L23:L25,$E$7)} -> 0.45 | M21: {=INDEX(M23:M25,$E$7)} -> 0.43 | N21: {=INDEX(N23:N25,$E$7)} -> 0.43 | ... P21: {=INDEX(P23:P25,$E$7)} -> 0.42
B23: =$B$11 -> Best Case | G23: 0.59 | H23: 0.55 | I23: 0.52 | J23: 0.49 | K23: 0.46 | L23: 0.43 | M23: 0.4 | N23: 0.4 | O23: 0.39 | P23: 0.39
B24: =$B$12 -> Base Case | G24: 0.61 | H24: 0.57 | I24: 0.54 | J24: 0.51 | K24: 0.48 | L24: 0.45 | M24: 0.43 | N24: 0.43 | O24: 0.42 | P24: 0.42
B25: =$B$13 -> Worst Case | G25: 0.63 | H25: 0.59 | I25: 0.56 | J25: 0.53 | K25: 0.5 | L25: 0.47 | M25: 0.45 | N25: 0.44 | O25: 0.425 | P25: 0.425
B27: R&D (% of Revenue) | G27: {=INDEX(G29:G31,$E$7)} -> 0.195 | H27: {=INDEX(H29:H31,$E$7)} -> 0.18 | I27: {=INDEX(I29:I31,$E$7)} -> 0.18 | J27: {=INDEX(J29:J31,$E$7)} -> 0.17 | K27: {=INDEX(K29:K31,$E$7)} -> 0.17 | L27: {=INDEX(L29:L31,$E$7)} -> 0.16 | M27: {=INDEX(M29:M31,$E$7)} -> 0.16 | N27: {=INDEX(N29:N31,$E$7)} -> 0.16 | ... P27: {=INDEX(P29:P31,$E$7)} -> 0.16
B29: =$B$11 -> Best Case | G29: 0.19 | H29: 0.17 | I29: 0.17 | J29: 0.16 | K29: 0.16 | L29: 0.15 | M29: 0.15 | N29: 0.15 | O29: 0.15 | P29: 0.15
B30: =$B$12 -> Base Case | G30: 0.195 | H30: 0.18 | I30: 0.18 | J30: 0.17 | K30: 0.17 | L30: 0.16 | M30: 0.16 | N30: 0.16 | O30: 0.16 | P30: 0.16
B31: =$B$13 -> Worst Case | G31: 0.21 | H31: 0.19 | I31: 0.19 | J31: 0.18 | K31: 0.18 | L31: 0.17 | M31: 0.17 | N31: 0.17 | O31: 0.165 | P31: 0.165
B33: D&A (% of Revenue) | G33: {=INDEX(G35:G37,$E$7)} -> 0.02 | H33: {=INDEX(H35:H37,$E$7)} -> 0.02 | I33: {=INDEX(I35:I37,$E$7)} -> 0.02 | J33: {=INDEX(J35:J37,$E$7)} -> 0.02 | K33: {=INDEX(K35:K37,$E$7)} -> 0.02 | L33: {=INDEX(L35:L37,$E$7)} -> 0.02 | M33: {=INDEX(M35:M37,$E$7)} -> 0.02 | N33: {=INDEX(N35:N37,$E$7)} -> 0.02 | ... P33: {=INDEX(P35:P37,$E$7)} -> 0.02
B35: =$B$11 -> Best Case | G35: 0.02 | H35: 0.02 | I35: 0.02 | J35: 0.02 | K35: 0.02 | L35: 0.02 | M35: 0.02 | N35: 0.02 | O35: 0.02 | P35: 0.02
B36: =$B$12 -> Base Case | G36: 0.02 | H36: 0.02 | I36: 0.02 | J36: 0.02 | K36: 0.02 | L36: 0.02 | M36: 0.02 | N36: 0.02 | O36: 0.02 | P36: 0.02
B37: =$B$13 -> Worst Case | G37: 0.02 | H37: 0.02 | I37: 0.02 | J37: 0.02 | K37: 0.02 | L37: 0.02 | M37: 0.02 | N37: 0.02 | O37: 0.02 | P37: 0.02
B40: Balance Sheet Drivers
B42: All figures in USD thousands unless stated | G42: 2025 | H42: =G42+1 -> 2026 | I42: =H42+1 -> 2027 | J42: =I42+1 -> 2028 | K42: =J42+1 -> 2029 | L42: =K42+1 -> 2030 | M42: =L42+1 -> 2031 | N42: =M42+1 -> 2032 | O42: =N42+1 -> 2033 | P42: =O42+1 -> 2034
B44: Driver Switch | E44: =$E$7 -> 2
B46: Accounts Receivable | G46: {=INDEX(G48:G50,$E$44)} -> 75 | H46: {=INDEX(H48:H50,$E$44)} -> 70 | I46: {=INDEX(I48:I50,$E$44)} -> 70 | J46: {=INDEX(J48:J50,$E$44)} -> 70 | K46: {=INDEX(K48:K50,$E$44)} -> 65 | L46: {=INDEX(L48:L50,$E$44)} -> 65 | M46: {=INDEX(M48:M50,$E$44)} -> 65 | N46: {=INDEX(N48:N50,$E$44)} -> 60 | ... P46: {=INDEX(P48:P50,$E$44)} -> 55
B48: =$B$11 -> Best Case | C48: (Days) | G48: 70 | H48: 65 | I48: 65 | J48: 65 | K48: 60 | L48: 60 | M48: 55 | N48: 55 | O48: 55 | P48: 50
B49: =$B$12 -> Base Case | C49: (Days) | G49: 75 | H49: 70 | I49: 70 | J49: 70 | K49: 65 | L49: 65 | M49: 65 | N49: 60 | O49: 60 | P49: 55
B50: =$B$13 -> Worst Case | C50: (Days) | G50: 80 | H50: 75 | I50: 75 | J50: 75 | K50: 70 | L50: 70 | M50: 70 | N50: 65 | O50: 65 | P50: 60
B52: Accounts Payable | G52: {=INDEX(G54:G56,$E$44)} -> 8 | H52: {=INDEX(H54:H56,$E$44)} -> 10 | I52: {=INDEX(I54:I56,$E$44)} -> 10 | J52: {=INDEX(J54:J56,$E$44)} -> 12 | K52: {=INDEX(K54:K56,$E$44)} -> 12 | L52: {=INDEX(L54:L56,$E$44)} -> 14 | M52: {=INDEX(M54:M56,$E$44)} -> 14 | N52: {=INDEX(N54:N56,$E$44)} -> 16 | ... P52: {=INDEX(P54:P56,$E$44)} -> 18
B54: =$B$11 -> Best Case | C54: (Days) | G54: 10 | H54: 12 | I54: 12 | J54: 14 | K54: 14 | L54: 16 | M54: 16 | N54: 18 | O54: 18 | P54: 20
B55: =$B$12 -> Base Case | C55: (Days) | G55: 8 | H55: 10 | I55: 10 | J55: 12 | K55: 12 | L55: 14 | M55: 14 | N55: 16 | O55: 16 | P55: 18
B56: =$B$13 -> Worst Case | C56: (Days) | G56: 6 | H56: 8 | I56: 8 | J56: 10 | K56: 10 | L56: 12 | M56: 12 | N56: 14 | O56: 14 | P56: 16
B59: Cashflow Statement Drivers
B61: All figures in USD thousands unless stated | G61: 2025 | H61: =G61+1 -> 2026 | I61: =H61+1 -> 2027 | J61: =I61+1 -> 2028 | K61: =J61+1 -> 2029 | L61: =K61+1 -> 2030 | M61: =L61+1 -> 2031 | N61: =M61+1 -> 2032 | O61: =N61+1 -> 2033 | P61: =O61+1 -> 2034
B63: Driver Switch | E63: =$E$7 -> 2
B65: Floating-Rate Benchmark: SOFR (projected annual) | G65: {=INDEX(G67:G69,$E$63)} -> 0.0425 | H65: {=INDEX(H67:H69,$E$63)} -> 0.0375 | I65: {=INDEX(I67:I69,$E$63)} -> 0.035 | J65: {=INDEX(J67:J69,$E$63)} -> 0.0325 | K65: {=INDEX(K67:K69,$E$63)} -> 0.03 | L65: {=INDEX(L67:L69,$E$63)} -> 0.03 | M65: {=INDEX(M67:M69,$E$63)} -> 0.03 | N65: {=INDEX(N67:N69,$E$63)} -> 0.03 | ... P65: {=INDEX(P67:P69,$E$63)} -> 0.03
B67: =$B$11 -> Best Case | C67: (bps) | G67: 0.0425 | H67: 0.0375 | I67: 0.035 | J67: 0.0325 | K67: 0.03 | L67: 0.03 | M67: 0.03 | N67: 0.03 | O67: 0.03 | P67: 0.03
B68: =$B$12 -> Base Case | C68: (bps) | G68: 0.0425 | H68: 0.0375 | I68: 0.035 | J68: 0.0325 | K68: 0.03 | L68: 0.03 | M68: 0.03 | N68: 0.03 | O68: 0.03 | P68: 0.03
B69: =$B$13 -> Worst Case | C69: (bps) | G69: 0.0425 | H69: 0.0375 | I69: 0.035 | J69: 0.0325 | K69: 0.03 | L69: 0.03 | M69: 0.03 | N69: 0.03 | O69: 0.03 | P69: 0.03
B71: CapEx (% of Revenue) | G71: {=INDEX(G73:G75,$E$7)} -> 0.02 | H71: {=INDEX(H73:H75,$E$7)} -> 0.02 | I71: {=INDEX(I73:I75,$E$7)} -> 0.02 | J71: {=INDEX(J73:J75,$E$7)} -> 0.02 | K71: {=INDEX(K73:K75,$E$7)} -> 0.02 | L71: {=INDEX(L73:L75,$E$7)} -> 0.02 | M71: {=INDEX(M73:M75,$E$7)} -> 0.02 | N71: {=INDEX(N73:N75,$E$7)} -> 0.02 | ... P71: {=INDEX(P73:P75,$E$7)} -> 0.02
B73: =$B$11 -> Best Case | G73: 0.02 | H73: 0.02 | I73: 0.02 | J73: 0.02 | K73: 0.02 | L73: 0.02 | M73: 0.02 | N73: 0.02 | O73: 0.02 | P73: 0.02
B74: =$B$12 -> Base Case | G74: 0.02 | H74: 0.02 | I74: 0.02 | J74: 0.02 | K74: 0.02 | L74: 0.02 | M74: 0.02 | N74: 0.02 | O74: 0.02 | P74: 0.02
B75: =$B$13 -> Worst Case | G75: 0.02 | H75: 0.02 | I75: 0.02 | J75: 0.02 | K75: 0.02 | L75: 0.02 | M75: 0.02 | N75: 0.02 | O75: 0.02 | P75: 0.02
B78: Financing Drivers
B80: Driver Switch | E80: =$E$7 -> 2 | G80: 2025 | H80: =G80+1 -> 2026 | I80: =H80+1 -> 2027 | J80: =I80+1 -> 2028 | K80: =J80+1 -> 2029 | L80: =K80+1 -> 2030 | M80: =L80+1 -> 2031 | N80: =M80+1 -> 2032 | O80: =N80+1 -> 2033 | P80: =O80+1 -> 2034
B82: Interest Income | G82: {=INDEX(G84:G86,$E$7)} -> 0.035 | H82: {=INDEX(H84:H86,$E$7)} -> 0.035 | I82: {=INDEX(I84:I86,$E$7)} -> 0.035 | J82: {=INDEX(J84:J86,$E$7)} -> 0.035 | K82: {=INDEX(K84:K86,$E$7)} -> 0.035 | L82: {=INDEX(L84:L86,$E$7)} -> 0.035 | M82: {=INDEX(M84:M86,$E$7)} -> 0.035 | N82: {=INDEX(N84:N86,$E$7)} -> 0.035 | ... P82: {=INDEX(P84:P86,$E$7)} -> 0.035
B84: =$B$11 -> Best Case | G84: 0.035 | H84: 0.035 | I84: 0.035 | J84: 0.035 | K84: 0.035 | L84: 0.035 | M84: 0.035 | N84: 0.035 | O84: 0.035 | P84: 0.035
B85: =$B$12 -> Base Case | G85: 0.035 | H85: 0.035 | I85: 0.035 | J85: 0.035 | K85: 0.035 | L85: 0.035 | M85: 0.035 | N85: 0.035 | O85: 0.035 | P85: 0.035
B86: =$B$13 -> Worst Case | G86: 0.035 | H86: 0.035 | I86: 0.035 | J86: 0.035 | K86: 0.035 | L86: 0.035 | M86: 0.035 | N86: 0.035 | O86: 0.035 | P86: 0.035
B88: Cash from Issuance of Equity | G88: {=INDEX(G90:G92,$E$7)} -> 0 | H88: {=INDEX(H90:H92,$E$7)} -> 0 | I88: {=INDEX(I90:I92,$E$7)} -> 0 | J88: {=INDEX(J90:J92,$E$7)} -> 0 | K88: {=INDEX(K90:K92,$E$7)} -> 0 | L88: {=INDEX(L90:L92,$E$7)} -> 0 | M88: {=INDEX(M90:M92,$E$7)} -> 0 | N88: {=INDEX(N90:N92,$E$7)} -> 0 | ... P88: {=INDEX(P90:P92,$E$7)} -> 0
B90: =$B$11 -> Best Case | G90: 0 | H90: 0 | I90: 0 | J90: 0 | K90: 0 | L90: 0 | M90: 0 | N90: 0 | O90: 0 | P90: 0
B91: =$B$12 -> Base Case | G91: 0 | H91: 0 | I91: 0 | J91: 0 | K91: 0 | L91: 0 | M91: 0 | N91: 0 | O91: 0 | P91: 0
B92: =$B$13 -> Worst Case | G92: 0 | H92: 0 | I92: 0 | J92: 0 | K92: 0 | L92: 0 | M92: 0 | N92: 0 | O92: 0 | P92: 0
B95: Cash Used to Repurchase Equity | G95: {=INDEX(G97:G99,$E$7)} -> 0 | H95: {=INDEX(H97:H99,$E$7)} -> 0 | I95: {=INDEX(I97:I99,$E$7)} -> 0 | J95: {=INDEX(J97:J99,$E$7)} -> 0 | K95: {=INDEX(K97:K99,$E$7)} -> 0 | L95: {=INDEX(L97:L99,$E$7)} -> 0 | M95: {=INDEX(M97:M99,$E$7)} -> 0 | N95: {=INDEX(N97:N99,$E$7)} -> 0 | ... P95: {=INDEX(P97:P99,$E$7)} -> 0
B97: =$B$11 -> Best Case | G97: 0 | H97: 0 | I97: 0 | J97: 0 | K97: 0 | L97: 0 | M97: 0 | N97: 0 | O97: 0 | P97: 0
B98: =$B$12 -> Base Case | G98: 0 | H98: 0 | I98: 0 | J98: 0 | K98: 0 | L98: 0 | M98: 0 | N98: 0 | O98: 0 | P98: 0
B99: =$B$13 -> Worst Case | G99: 0 | H99: 0 | I99: 0 | J99: 0 | K99: 0 | L99: 0 | M99: 0 | N99: 0 | O99: 0 | P99: 0

Sheet Model
B1: LBO Model & Schedules
B3: Income Statement
B5: All figures in USD thousands unless stated | J5: =K5-1 -> 2024 | K5: ='Transaction Assumptions'!J24 -> 2025 | L5: =K5+1 -> 2026 | M5: =L5+1 -> 2027 | N5: =M5+1 -> 2028 | O5: =N5+1 -> 2029 | P5: =O5+1 -> 2030 | Q5: =P5+1 -> 2031 | R5: =Q5+1 -> 2032 | S5: =R5+1 -> 2033 | T5: =S5+1 -> 2034
B6: {=CONCATENATE("Model Running: ",INDEX('Forecasting Assumptions'!$B$11:$B$13,'Forecasting Assumptions'!$E$7)," Drivers")} -> Model Running: Base Case Drivers
B8: Revenues | J8: =IS!D6 -> 958338 | K8: =J8*(1+'Forecasting Assumptions'!G9) -> 1245839.4 | L8: =K8*(1+'Forecasting Assumptions'!H9) -> 1619591.2 | M8: =L8*(1+'Forecasting Assumptions'!I9) -> 2105468.6 | N8: =M8*(1+'Forecasting Assumptions'!J9) -> 2716054.5 | O8: =N8*(1+'Forecasting Assumptions'!K9) -> 3503710.3 | P8: =O8*(1+'Forecasting Assumptions'!L9) -> 4460223.2 | Q8: =P8*(1+'Forecasting Assumptions'!M9) -> 5468233.6 | R8: =Q8*(1+'Forecasting Assumptions'!N9) -> 6441579.2 | ... T8: =S8*(1+'Forecasting Assumptions'!P9) -> 7897401.9
B9: COGS | J9: =IS!D10 -> 186448 | K9: =K8-K10 -> 236709.49 | L9: =L8-L10 -> 307722.33 | M9: =M8-M10 -> 400039.03 | N9: =N8-N10 -> 516050.35 | O9: =O8-O10 -> 665704.95 | P9: =P8-P10 -> 847442.4 | Q9: =Q8-Q10 -> 1038964.4 | R9: =R8-R10 -> 1223900 | ... T9: =T8-T10 -> 1500506.4
B10: Gross Margin | J10: =J8-J9 -> 771890 | K10: =K8*'Forecasting Assumptions'!G15 -> 1009129.9 | L10: =L8*'Forecasting Assumptions'!H15 -> 1311868.9 | M10: =M8*'Forecasting Assumptions'!I15 -> 1705429.6 | N10: =N8*'Forecasting Assumptions'!J15 -> 2200004.1 | O10: =O8*'Forecasting Assumptions'!K15 -> 2838005.3 | P10: =P8*'Forecasting Assumptions'!L15 -> 3612780.8 | Q10: =Q8*'Forecasting Assumptions'!M15 -> 4429269.2 | R10: =R8*'Forecasting Assumptions'!N15 -> 5217679.2 | ... T10: =T8*'Forecasting Assumptions'!P15 -> 6396895.5
B12: SG&A | J12: =IS!D14+IS!D15 -> 658101 | K12: =K8*'Forecasting Assumptions'!G21 -> 759962.03 | L12: =L8*'Forecasting Assumptions'!H21 -> 923167 | M12: =M8*'Forecasting Assumptions'!I21 -> 1136953 | N12: =N8*'Forecasting Assumptions'!J21 -> 1385187.8 | O12: =O8*'Forecasting Assumptions'!K21 -> 1681780.9 | P12: =P8*'Forecasting Assumptions'!L21 -> 2007100.4 | Q12: =Q8*'Forecasting Assumptions'!M21 -> 2351340.5 | R12: =R8*'Forecasting Assumptions'!N21 -> 2769879.1 | ... T12: =T8*'Forecasting Assumptions'!P21 -> 3316908.8
B13: R&D | J13: =IS!D13 -> 234071 | K13: =K8*'Forecasting Assumptions'!G27 -> 242938.68 | L13: =L8*'Forecasting Assumptions'!H27 -> 291526.42 | M13: =M8*'Forecasting Assumptions'!I27 -> 378984.35 | N13: =N8*'Forecasting Assumptions'!J27 -> 461729.26 | O13: =O8*'Forecasting Assumptions'!K27 -> 595630.75 | P13: =P8*'Forecasting Assumptions'!L27 -> 713635.71 | Q13: =Q8*'Forecasting Assumptions'!M27 -> 874917.38 | R13: =R8*'Forecasting Assumptions'!N27 -> 1030652.7 | ... T13: =T8*'Forecasting Assumptions'!P27 -> 1263584.3
B14: EBIT | J14: =J10-J12-J13 -> -120282 | K14: =K10-K12-K13 -> 6229.197 | L14: =L10-L12-L13 -> 97175.473 | M14: =M10-M12-M13 -> 189492.17 | N14: =N10-N12-N13 -> 353087.08 | O14: =O10-O12-O13 -> 560593.64 | P14: =P10-P12-P13 -> 892044.64 | Q14: =Q10-Q12-Q13 -> 1203011.4 | ... T14: =T10-T12-T13 -> 1816402.4
B16: *Depreciation | J16: =J118 -> 27012 | K16: =K118 -> 24916.788 | L16: =L118 -> 32391.824 | M16: =M118 -> 42109.372 | N16: =N118 -> 54321.09 | O16: =O118 -> 70074.205 | P16: =P118 -> 89204.464 | Q16: =Q118 -> 109364.67 | ... T16: =T118 -> 157948.04
B17: *EBITDA | J17: =J14+J16 -> -93270 | K17: =K14+K16 -> 31145.985 | L17: =L14+L16 -> 129567.3 | M17: =M14+M16 -> 231601.54 | N17: =N14+N16 -> 407408.17 | O17: =O14+O16 -> 630667.85 | P17: =P14+P16 -> 981249.1 | Q17: =Q14+Q16 -> 1312376.1 | ... T17: =T14+T16 -> 1974350.5
B19: Cash Net Interest Expense (Income) | J19: =-(IS!D19+IS!D18) -> -24140 | K19: =K303 -> 70934.69 | L19: =L303 -> 69018.63 | M19: =M303 -> 70443.15 | N19: =N303 -> 69594.436 | O19: =O303 -> 63701.354 | P19: =P303 -> 158222.44 | Q19: =Q303 -> 147147.81 | R19: =R303 -> 128095.35 | ... T19: =T303 -> 65382.648
B20: PIK Interest Expense | J20: 0 | K20: =K304 -> 111546.48 | L20: =L304 -> 119912.47 | M20: =M304 -> 128905.9 | N20: =N304 -> 138573.84 | O20: =O304 -> 148966.88 | P20: =P304 -> 53379.799 | Q20: =Q304 -> 54714.294 | R20: =R304 -> 56082.151 | ... T20: =T304 -> 58921.31
B21: Total Interest Expense | J21: =SUM(J19:J20) -> -24140 | K21: =SUM(K19:K20) -> 182481.17 | L21: =SUM(L19:L20) -> 188931.1 | M21: =SUM(M19:M20) -> 199349.05 | N21: =SUM(N19:N20) -> 208168.28 | O21: =SUM(O19:O20) -> 212668.23 | P21: =SUM(P19:P20) -> 211602.24 | Q21: =SUM(Q19:Q20) -> 201862.1 | ... T21: =SUM(T19:T20) -> 124303.96
B22: EBT | J22: =J14-J19 -> -96142 | K22: =K14-K21 -> -176251.97 | L22: =L14-L21 -> -91755.622 | M22: =M14-M21 -> -9856.8775 | N22: =N14-N21 -> 144918.8 | O22: =O14-O21 -> 347925.41 | P22: =P14-P21 -> 680442.4 | Q22: =Q14-Q21 -> 1001149.3 | R22: =R14-R21 -> 1232969.9 | ... T22: =T14-T21 -> 1692098.5
B24: Current Taxes | J24: =IS!D21 -> 8489 | K24: =K166 -> 0 | L24: =L166 -> 0 | M24: =M166 -> 0 | N24: =N166 -> 0 | O24: =O166 -> 0 | P24: =P166 -> 126705.53 | Q24: =Q166 -> 250287.32 | R24: =R166 -> 308242.48 | ... T24: =T166 -> 423024.62
B25: Deferred Taxes | J25: 0 | K25: =K167 -> 0 | L25: =L167 -> 0 | M25: =M167 -> 0 | N25: =N167 -> 36229.701 | O25: =O167 -> 86981.352 | P25: =P167 -> 43405.065 | Q25: =Q167 -> 0 | R25: =R167 -> 0 | ... T25: =T167 -> 0
B26: Total Tax Expense | J26: =SUM(J24:J25) -> 8489 | K26: =SUM(K24:K25) -> 0 | L26: =SUM(L24:L25) -> 0 | M26: =SUM(M24:M25) -> 0 | N26: =SUM(N24:N25) -> 36229.701 | O26: =SUM(O24:O25) -> 86981.352 | P26: =SUM(P24:P25) -> 170110.6 | Q26: =SUM(Q24:Q25) -> 250287.32 | ... T26: =SUM(T24:T25) -> 423024.62
B27: Net Income | J27: =J22-J26 -> -104631 | K27: =K22-K26 -> -176251.97 | L27: =L22-L26 -> -91755.622 | M27: =M22-M26 -> -9856.8775 | N27: =N22-N26 -> 108689.1 | O27: =O22-O26 -> 260944.06 | P27: =P22-P26 -> 510331.8 | Q27: =Q22-Q26 -> 750861.97 | ... T27: =T22-T26 -> 1269073.9
B30: Balance Sheet
B32: All figures in USD thousands unless stated | H32: =$J$5 -> 2024 | I32: Incr / Decr | J32: 2024 Adj | K32: =$K$5 -> 2025 | L32: =$L$5 -> 2026 | M32: =$M$5 -> 2027 | N32: =$N$5 -> 2028 | O32: =$O$5 -> 2029 | P32: =$P$5 -> 2030 | Q32: =$Q$5 -> 2031 | R32: =$R$5 -> 2032 | S32: =$S$5 -> 2033 | T32: =$T$5 -> 2034
B33: =$B$6 -> Model Running: Base Case Drivers
B35: Assets
B36: Cash (Incl. short term investments) | H36: =BS!$C$4+BS!$C$5 -> 628795 | I36: =-'Transaction Assumptions'!J8 -> -428795 | J36: =SUM(H36:I36) -> 200000 | K36: =J36+K83 -> 5000 | L36: =K36+L83 -> 5000 | M36: =L36+M83 -> 5000 | N36: =M36+N83 -> 5000 | O36: =N36+O83 -> 154820.03 | P36: =O36+P83 -> 587053.08 | Q36: =P36+Q83 -> 1250119.7 | R36: =Q36+R83 -> 2190769.9 | ... T36: =S36+T83 -> 4671535.4
B37: Accounts Receivable | H37: =BS!$C$6 -> 238708 | I37: 0 | J37: =SUM(H37:I37) -> 238708 | K37: =K101 -> 255994.4 | L37: =L101 -> 310606.54 | M37: =M101 -> 403788.5 | N37: =N101 -> 520887.16 | O37: =O101 -> 623948.4 | P37: =P101 -> 794286.32 | Q37: =Q101 -> 973795.03 | R37: =R101 -> 1058889.7 | ... T37: =T101 -> 1190019.5
B38: Goodwill | H38: =BS!$C$14 -> 141477 | I38: ='Transaction Assumptions'!$N$8-($H$49+$H$50) -> 6109537.7 | J38: =SUM(H38:I38) -> 6251014.7 | K38: =J38 -> 6251014.7 | L38: =K38 -> 6251014.7 | M38: =L38 -> 6251014.7 | N38: =M38 -> 6251014.7 | O38: =N38 -> 6251014.7 | P38: =O38 -> 6251014.7 | Q38: =P38 -> 6251014.7 | R38: =Q38 -> 6251014.7 | ... T38: =S38 -> 6251014.7
B39: Other Assets | H39: =BS!$C$7+BS!$C$9+BS!$C$10+BS!$C$12+BS!$C$13+BS!$C$15 -> 286137 | I39: 0 | J39: =SUM(H39:I39) -> 286137 | K39: =J39*1.05 -> 300443.85 | L39: =K39*1.05 -> 315466.04 | M39: =L39*1.05 -> 331239.34 | N39: =M39*1.05 -> 347801.31 | O39: =N39*1.05 -> 365191.38 | P39: =O39*1.05 -> 383450.95 | Q39: =P39*1.05 -> 402623.49 | R39: =Q39*1.05 -> 422754.67 | ... T39: =S39*1.05 -> 466087.02
B40: PPE (ending) | H40: =$J$136 -> 42362 | I40: 0 | J40: =SUM(H40:I40) -> 42362 | K40: =K136 -> 42362 | L40: =L136 -> 42362 | M40: =M136 -> 42362 | N40: =N136 -> 42362 | O40: =O136 -> 42362 | P40: =P136 -> 42362 | Q40: =Q136 -> 42362 | R40: =R136 -> 42362 | ... T40: =T136 -> 42362
B41: Assets(total) | H41: =SUM(H36:H40) -> 1337479 | J41: =SUM(J36:J40) -> 7018221.7 | K41: =SUM(K36:K40) -> 6854814.9 | L41: =SUM(L36:L40) -> 6924449.3 | M41: =SUM(M36:M40) -> 7033404.5 | N41: =SUM(N36:N40) -> 7167065.2 | O41: =SUM(O36:O40) -> 7437336.5 | P41: =SUM(P36:P40) -> 8058167 | Q41: =SUM(Q36:Q40) -> 8919914.9 | ... T41: =SUM(T36:T40) -> 12621019
B43: Liabilities & Equity
B44: Accounting Payable | H44: =BS!$C$18 -> 2937 | I44: 0 | J44: =SUM(H44:I44) -> 2937 | K44: =K102 -> 5188.1531 | L44: =L102 -> 8430.7488 | M44: =M102 -> 10959.973 | N44: =N102 -> 16966.039 | O44: =O102 -> 21886.19 | P44: =P102 -> 32504.64 | Q44: =Q102 -> 39850.689 | R44: =R102 -> 53650.413 | ... T44: =T102 -> 73997.574
B45: Revolving Credit Line | H45: 0 | I45: ='Transaction Assumptions'!$J$12 -> 0 | J45: =SUM(H45:I45) -> 0 | K45: =K286 -> 0 | L45: =L286 -> 54061.966 | M45: =M286 -> 55353.252 | N45: =N286 -> 0 | O45: =O286 -> 0 | P45: =P286 -> 0 | Q45: =Q286 -> 0 | R45: =R286 -> 0 | ... T45: =T286 -> 0
B46: Term Loan A | H46: 0 | I46: ='Transaction Assumptions'!$J$9 -> 540831.42 | J46: =SUM(H46:I46) -> 540831.42 | K46: =K287 -> 403444.65 | L46: =L287 -> 349361.51 | M46: =M287 -> 295278.37 | N46: =N287 -> 188845.93 | O46: =O287 -> 0 | P46: =P287 -> 0 | Q46: =Q287 -> 0 | R46: =R287 -> 0 | ... T46: =T287 -> 0
B47: Subordinated Debt | H47: 0 | I47: ='Transaction Assumptions'!$J$10 -> 1487286.4 | J47: =SUM(H47:I47) -> 1487286.4 | K47: =K288 -> 1598832.9 | L47: =L288 -> 1718745.3 | M47: =M288 -> 1847651.2 | N47: =N288 -> 1986225.1 | O47: =O288 -> 2135192 | P47: =P288 -> 2188571.8 | Q47: =Q288 -> 2243286.1 | R47: =R288 -> 2299368.2 | ... T47: =T288 -> 2415773.7
B48: Other Liabilities | H48: =BS!$C$19+BS!$C$20+BS!$C$21+BS!$C$22+BS!$C$23+BS!$C$25+BS!$C$26+BS!$C$27+BS!$C$28 -> 728687 | I48: 0 | J48: =SUM(H48:I48) -> 728687 | K48: =J48*1.05 -> 765121.35 | L48: =K48*1.05 -> 803377.42 | M48: =L48*1.05 -> 843546.29 | N48: =M48*1.05 -> 885723.6 | O48: =N48*1.05 -> 930009.78 | P48: =O48*1.05 -> 976510.27 | Q48: =P48*1.05 -> 1025335.8 | R48: =Q48*1.05 -> 1076602.6 | ... T48: =S48*1.05 -> 1186954.3
B49: Common Stock | H49: =BS!$C$31 -> 1468805 | I49: 0 | J49: ='Transaction Assumptions'!J11 -> 4303479.9 | K49: =J49+K77 -> 4303479.9 | L49: =K49+L77 -> 4303479.9 | M49: =L49+M77 -> 4303479.9 | N49: =M49+N77 -> 4303479.9 | O49: =N49+O77 -> 4303479.9 | P49: =O49+P77 -> 4303479.9 | Q49: =P49+Q77 -> 4303479.9 | R49: =Q49+R77 -> 4303479.9 | ... T49: =S49+T77 -> 4303479.9
B50: Retained Earnings (Accumulated Deficit) | H50: =BS!$C$32+BS!$C$33 -> -862950 | I50: 0 | J50: =-'Transaction Assumptions'!N10 -> -45000 | K50: =J50+K27+K78 -> -221251.97 | L50: =K50+L27+L78 -> -313007.59 | M50: =L50+M27+M78 -> -322864.47 | N50: =M50+N27+N78 -> -214175.37 | O50: =N50+O27+O78 -> 46768.687 | P50: =O50+P27+P78 -> 557100.49 | Q50: =P50+Q27+Q78 -> 1307962.5 | R50: =Q50+R27+R78 -> 2232689.9 | ... T50: =S50+T27+T78 -> 4640813.1
B51: Total L. & E. | H51: =SUM(H44:H50) -> 1337479 | J51: =SUM(J44:J50) -> 7018221.7 | K51: =SUM(K44:K50) -> 6854814.9 | L51: =SUM(L44:L50) -> 6924449.3 | M51: =SUM(M44:M50) -> 7033404.5 | N51: =SUM(N44:N50) -> 7167065.2 | O51: =SUM(O44:O50) -> 7437336.5 | P51: =SUM(P44:P50) -> 8058167 | Q51: =SUM(Q44:Q50) -> 8919914.9 | ... T51: =SUM(T44:T50) -> 12621019
B53: Balance Check | J53: =J41-J51 -> 0 | K53: =K41-K51 -> 0 | L53: =L41-L51 -> 0 | M53: =M41-M51 -> 0 | N53: =N41-N51 -> 0 | O53: =O41-O51 -> 0 | P53: =P41-P51 -> 0 | Q53: =Q41-Q51 -> 0 | ... T53: =T41-T51 -> 0
B56: Cash Flow Statement
B58: All figures in USD thousands unless stated | J58: =$J$5 -> 2024 | K58: =$K$5 -> 2025 | L58: =$L$5 -> 2026 | M58: =$M$5 -> 2027 | N58: =$N$5 -> 2028 | O58: =$O$5 -> 2029 | P58: =$P$5 -> 2030 | Q58: =$Q$5 -> 2031 | R58: =$R$5 -> 2032 | S58: =$S$5 -> 2033 | T58: =$T$5 -> 2034
B59: =$B$6 -> Model Running: Base Case Drivers
B61: Cash Flow Statement
B62: Net Income | J62: =J27 -> -104631 | K62: =K27 -> -176251.97 | L62: =L27 -> -91755.622 | M62: =M27 -> -9856.8775 | N62: =N27 -> 108689.1 | O62: =O27 -> 260944.06 | P62: =P27 -> 510331.8 | Q62: =Q27 -> 750861.97 | ... T62: =T27 -> 1269073.9
B63: Depreciation | J63: =J118 -> 27012 | K63: =K118 -> 24916.788 | L63: =L118 -> 32391.824 | M63: =M118 -> 42109.372 | N63: =N118 -> 54321.09 | O63: =O118 -> 70074.205 | P63: =P118 -> 89204.464 | Q63: =Q118 -> 109364.67 | ... T63: =T118 -> 157948.04
B64: PIK Interest expense | K64: =K248 -> 111546.48 | L64: =L248 -> 119912.47 | M64: =M248 -> 128905.9 | N64: =N248 -> 138573.84 | O64: =O248 -> 148966.88 | P64: =P248 -> 53379.799 | Q64: =Q248 -> 54714.294 | R64: =R248 -> 56082.151 | ... T64: =T248 -> 58921.31
B65: ∆ Net Working Capital | K65: =K110 -> -15035.244 | L65: =L110 -> -51369.542 | M65: =M110 -> -90652.736 | N65: =N110 -> -111092.6 | O65: =O110 -> -98141.094 | P65: =P110 -> -159719.46 | Q65: =Q110 -> -172162.66 | R65: =R110 -> -71294.98 | ... T65: =T110 -> 20903.784
B66: ∆ Other Operating Assets | K66: =-(SUM(K38:K40)-SUM(J38:J40)) -> -14306.85 | L66: =-(SUM(L38:L40)-SUM(K38:K40)) -> -15022.193 | M66: =-(SUM(M38:M40)-SUM(L38:L40)) -> -15773.302 | N66: =-(SUM(N38:N40)-SUM(M38:M40)) -> -16561.967 | O66: =-(SUM(O38:O40)-SUM(N38:N40)) -> -17390.066 | P66: =-(SUM(P38:P40)-SUM(O38:O40)) -> -18259.569 | Q66: =-(SUM(Q38:Q40)-SUM(P38:P40)) -> -19172.547 | R66: =-(SUM(R38:R40)-SUM(Q38:Q40)) -> -20131.175 | ... T66: =-(SUM(T38:T40)-SUM(S38:S40)) -> -22194.62
B67: ∆ Other Operating Liabilities | K67: =K48-J48 -> 36434.35 | L67: =L48-K48 -> 38256.068 | M67: =M48-L48 -> 40168.871 | N67: =N48-M48 -> 42177.314 | O67: =O48-N48 -> 44286.18 | P67: =P48-O48 -> 46500.489 | Q67: =Q48-P48 -> 48825.514 | R67: =R48-Q48 -> 51266.789 | ... T67: =T48-S48 -> 56521.635
B68: CFO | K68: =SUM(K62:K67) -> -32696.449 | L68: =SUM(L62:L67) -> 32413 | M68: =SUM(M62:M67) -> 94901.227 | N68: =SUM(N62:N67) -> 216106.78 | O68: =SUM(O62:O67) -> 408740.16 | P68: =SUM(P62:P67) -> 521437.52 | Q68: =SUM(Q62:Q67) -> 772431.24 | R68: =SUM(R62:R67) -> 1069481.8 | ... T68: =SUM(T62:T67) -> 1541174
B70: Cash Flow Investment
B71: Capital Expenditures | K71: =-K121 -> -24916.788 | L71: =-L121 -> -32391.824 | M71: =-M121 -> -42109.372 | N71: =-N121 -> -54321.09 | O71: =-O121 -> -70074.205 | P71: =-P121 -> -89204.464 | Q71: =-Q121 -> -109364.67 | R71: =-R121 -> -128831.58 | ... T71: =-T121 -> -157948.04
B73: Cash Flow Financing
B74: Revolving Credit Line Issuance / (Repayment) | K74: =K192 -> 0 | L74: =L192 -> 54061.966 | M74: =M192 -> 1291.286 | N74: =N192 -> -55353.252 | O74: =O192 -> 0 | P74: =P192 -> 0 | Q74: =Q192 -> 0 | R74: =R192 -> 0 | ... T74: =T192 -> 0
B75: Term Loan A Issuance / (Repayment) | K75: =SUM(K229:K230) -> -137386.76 | L75: =SUM(L229:L230) -> -54083.142 | M75: =SUM(M229:M230) -> -54083.142 | N75: =SUM(N229:N230) -> -106432.44 | O75: =SUM(O229:O230) -> -188845.93 | P75: =SUM(P229:P230) -> 0 | Q75: =SUM(Q229:Q230) -> 0 | R75: =SUM(R229:R230) -> 0 | ... T75: =SUM(T229:T230) -> 0
B76: Subordinated Debt Issuance / (Repayment) | K76: =K247 -> 0 | L76: =L247 -> 0 | M76: =M247 -> 0 | N76: =N247 -> 0 | O76: =O247 -> 0 | P76: =P247 -> 0 | Q76: =Q247 -> 0 | R76: =R247 -> 0 | ... T76: =T247 -> 0
B77: Equity Issuance / (Repurchase) | K77: =SUM(K316:K317) -> 0 | L77: =SUM(L316:L317) -> 0 | M77: =SUM(M316:M317) -> 0 | N77: =SUM(N316:N317) -> 0 | O77: =SUM(O316:O317) -> 0 | P77: =SUM(P316:P317) -> 0 | Q77: =SUM(Q316:Q317) -> 0 | R77: =SUM(R316:R317) -> 0 | ... T77: =SUM(T316:T317) -> 0
B78: Payment of Dividends | K78: =K324 -> 0 | L78: 0 | M78: 0 | N78: 0 | O78: 0 | P78: 0 | Q78: 0 | R78: 0 | S78: 0 | T78: 0
B79: CFF | K79: =SUM(K74:K78) -> -137386.76 | L79: =SUM(L74:L78) -> -21.175759 | M79: =SUM(M74:M78) -> -52791.856 | N79: =SUM(N74:N78) -> -161785.69 | O79: =SUM(O74:O78) -> -188845.93 | P79: =SUM(P74:P78) -> 0 | Q79: =SUM(Q74:Q78) -> 0 | R79: =SUM(R74:R78) -> 0 | ... T79: =SUM(T74:T78) -> 0
B81: Cash Balance
B82: Beginning Cash Balance | K82: =J36 -> 200000 | L82: =K84 -> 5000 | M82: =L84 -> 5000 | N82: =M84 -> 5000 | O82: =N84 -> 5000 | P82: =O84 -> 154820.03 | Q82: =P84 -> 587053.08 | R82: =Q84 -> 1250119.7 | S82: =R84 -> 2190769.9 | T82: =S84 -> 3288309.5
B83: Change in Cash | K83: =K68+K71+K79 -> -195000 | L83: =L68+L71+L79 -> 0 | M83: =M68+M71+M79 -> 0 | N83: =N68+N71+N79 -> 0 | O83: =O68+O71+O79 -> 149820.03 | P83: =P68+P71+P79 -> 432233.05 | Q83: =Q68+Q71+Q79 -> 663066.57 | R83: =R68+R71+R79 -> 940650.23 | ... T83: =T68+T71+T79 -> 1383226
B84: End | K84: =SUM(K82:K83) -> 5000 | L84: =SUM(L82:L83) -> 5000 | M84: =SUM(M82:M83) -> 5000 | N84: =SUM(N82:N83) -> 5000 | O84: =SUM(O82:O83) -> 154820.03 | P84: =SUM(P82:P83) -> 587053.08 | Q84: =SUM(Q82:Q83) -> 1250119.7 | R84: =SUM(R82:R83) -> 2190769.9 | ... T84: =SUM(T82:T83) -> 4671535.4
B87: Working Capital Schedule
B89: All figures in USD thousands unless stated | H89: =I89-1 -> 2022 | I89: =J89-1 -> 2023 | J89: =$J$5 -> 2024 | K89: =$K$5 -> 2025 | L89: =$L$5 -> 2026 | M89: =$M$5 -> 2027 | N89: =$N$5 -> 2028 | O89: =$O$5 -> 2029 | P89: =$P$5 -> 2030 | Q89: =$Q$5 -> 2031 | R89: =$R$5 -> 2032 | S89: =$S$5 -> 2033 | T89: =$T$5 -> 2034
B90: =$B$6 -> Model Running: Base Case Drivers
B92: Days in Period | H92: 365 | I92: 365 | J92: 365 | K92: 365 | L92: 365 | M92: 365 | N92: 365 | O92: 365 | P92: 365 | Q92: 365 | R92: 365 | S92: 365 | T92: 365
B93: Revenue | H93: 550832 | I93: 766915 | J93: 958338 | K93: =K8 -> 1245839.4 | L93: =L8 -> 1619591.2 | M93: =M8 -> 2105468.6 | N93: =N8 -> 2716054.5 | O93: =O8 -> 3503710.3 | P93: =P8 -> 4460223.2 | Q93: =Q8 -> 5468233.6 | R93: =R8 -> 6441579.2 | ... T93: =T8 -> 7897401.9
B94: COGS | H94: 116473 | I94: 165285 | J94: 186448 | K94: =K9 -> 236709.49 | L94: =L9 -> 307722.33 | M94: =M9 -> 400039.03 | N94: =N9 -> 516050.35 | O94: =O9 -> 665704.95 | P94: =P9 -> 847442.4 | Q94: =Q9 -> 1038964.4 | R94: =R9 -> 1223900 | ... T94: =T9 -> 1500506.4
B96: AMOUNTS PER DAY
C97: Accounts Receivable (DSO) | F97: (Days) | H97: =(H101/H93)*H92 -> 100.14917 | I97: =(I101/I93)*I92 -> 94.540718 | J97: =(J101/J93)*J92 -> 90.916169 | K97: ='Forecasting Assumptions'!G46 -> 75 | L97: ='Forecasting Assumptions'!H46 -> 70 | M97: ='Forecasting Assumptions'!I46 -> 70 | N97: ='Forecasting Assumptions'!J46 -> 70 | O97: ='Forecasting Assumptions'!K46 -> 65 | P97: ='Forecasting Assumptions'!L46 -> 65 | Q97: ='Forecasting Assumptions'!M46 -> 65 | R97: ='Forecasting Assumptions'!N46 -> 60 | ... T97: ='Forecasting Assumptions'!P46 -> 55
C98: Accounts Payable (DPO) | F98: (Days) | H98: =(H102/H94)*H92 -> 4.7194629 | I98: =(I102/I94)*I92 -> 4.6926521 | J98: =(J102/J94)*J92 -> 5.7496192 | K98: ='Forecasting Assumptions'!G52 -> 8 | L98: ='Forecasting Assumptions'!H52 -> 10 | M98: ='Forecasting Assumptions'!I52 -> 10 | N98: ='Forecasting Assumptions'!J52 -> 12 | O98: ='Forecasting Assumptions'!K52 -> 12 | P98: ='Forecasting Assumptions'!L52 -> 14 | Q98: ='Forecasting Assumptions'!M52 -> 14 | R98: ='Forecasting Assumptions'!N52 -> 16 | ... T98: ='Forecasting Assumptions'!P52 -> 18
B100: TOTAL AMOUNTS
C101: Accounts Receivable | H101: 151138 | I101: 198643 | J101: 238708 | K101: =(K97/K92)*K93 -> 255994.4 | L101: =(L97/L92)*L93 -> 310606.54 | M101: =(M97/M92)*M93 -> 403788.5 | N101: =(N97/N92)*N93 -> 520887.16 | O101: =(O97/O92)*O93 -> 623948.4 | P101: =(P97/P92)*P93 -> 794286.32 | Q101: =(Q97/Q92)*Q93 -> 973795.03 | R101: =(R97/R92)*R93 -> 1058889.7 | ... T101: =(T97/T92)*T93 -> 1190019.5
C102: Accounts Payable | H102: 1506 | I102: 2125 | J102: 2937 | K102: =(K98/K92)*K94 -> 5188.1531 | L102: =(L98/L92)*L94 -> 8430.7488 | M102: =(M98/M92)*M94 -> 10959.973 | N102: =(N98/N92)*N94 -> 16966.039 | O102: =(O98/O92)*O94 -> 21886.19 | P102: =(P98/P92)*P94 -> 32504.64 | Q102: =(Q98/Q92)*Q94 -> 39850.689 | R102: =(R98/R92)*R94 -> 53650.413 | ... T102: =(T98/T92)*T94 -> 73997.574
B105: NET WORKING CAPITAL
C106: Current Assets | H106: =H101 -> 151138 | I106: =I101 -> 198643 | J106: =J101 -> 238708 | K106: =K101 -> 255994.4 | L106: =L101 -> 310606.54 | M106: =M101 -> 403788.5 | N106: =N101 -> 520887.16 | O106: =O101 -> 623948.4 | ... T106: =T101 -> 1190019.5
C107: Current Liabilities | H107: =SUM(H102) -> 1506 | I107: =SUM(I102) -> 2125 | J107: =SUM(J102) -> 2937 | K107: =SUM(K102) -> 5188.1531 | L107: =SUM(L102) -> 8430.7488 | M107: =SUM(M102) -> 10959.973 | N107: =SUM(N102) -> 16966.039 | O107: =SUM(O102) -> 21886.19 | ... T107: =SUM(T102) -> 73997.574
C108: Net Working Capital | H108: =H106-H107 -> 149632 | I108: =I106-I107 -> 196518 | J108: =J106-J107 -> 235771 | K108: =K106-K107 -> 250806.24 | L108: =L106-L107 -> 302175.79 | M108: =M106-M107 -> 392828.52 | N108: =N106-N107 -> 503921.12 | O108: =O106-O107 -> 602062.21 | ... T108: =T106-T107 -> 1116021.9
C110: Cash from Working Capital Items | K110: =J108-K108 -> -15035.244 | L110: =K108-L108 -> -51369.542 | M110: =L108-M108 -> -90652.736 | N110: =M108-N108 -> -111092.6 | O110: =N108-O108 -> -98141.094 | P110: =O108-P108 -> -159719.46 | Q110: =P108-Q108 -> -172162.66 | R110: =Q108-R108 -> -71294.98 | ... T110: =S108-T108 -> 20903.784
B113: D&A and CapEx Schedule
B115: All figures in USD thousands unless stated | J115: =$J$5 -> 2024 | K115: =$K$5 -> 2025 | L115: =$L$5 -> 2026 | M115: =$M$5 -> 2027 | N115: =$N$5 -> 2028 | O115: =$O$5 -> 2029 | P115: =$P$5 -> 2030 | Q115: =$Q$5 -> 2031 | R115: =$R$5 -> 2032 | S115: =$S$5 -> 2033 | T115: =$T$5 -> 2034
B116: =$B$6 -> Model Running: Base Case Drivers
B118: Depreciation and Amortization | J118: =IS!D27 -> 27012 | K118: =K8*K119 -> 24916.788 | L118: =L8*L119 -> 32391.824 | M118: =M8*M119 -> 42109.372 | N118: =N8*N119 -> 54321.09 | O118: =O8*O119 -> 70074.205 | P118: =P8*P119 -> 89204.464 | Q118: =Q8*Q119 -> 109364.67 | R118: =R8*R119 -> 128831.58 | ... T118: =T8*T119 -> 157948.04
C119: % growth | K119: ='Forecasting Assumptions'!G33 -> 0.02 | L119: ='Forecasting Assumptions'!H33 -> 0.02 | M119: ='Forecasting Assumptions'!I33 -> 0.02 | N119: ='Forecasting Assumptions'!J33 -> 0.02 | O119: ='Forecasting Assumptions'!K33 -> 0.02 | P119: ='Forecasting Assumptions'!L33 -> 0.02 | Q119: ='Forecasting Assumptions'!M33 -> 0.02 | R119: ='Forecasting Assumptions'!N33 -> 0.02 | ... T119: ='Forecasting Assumptions'!P33 -> 0.02
B121: Capital Expenditure | K121: =K8*K122 -> 24916.788 | L121: =L8*L122 -> 32391.824 | M121: =M8*M122 -> 42109.372 | N121: =N8*N122 -> 54321.09 | O121: =O8*O122 -> 70074.205 | P121: =P8*P122 -> 89204.464 | Q121: =Q8*Q122 -> 109364.67 | R121: =R8*R122 -> 128831.58 | ... T121: =T8*T122 -> 157948.04
C122: % growth | K122: ='Forecasting Assumptions'!G71 -> 0.02 | L122: ='Forecasting Assumptions'!H71 -> 0.02 | M122: ='Forecasting Assumptions'!I71 -> 0.02 | N122: ='Forecasting Assumptions'!J71 -> 0.02 | O122: ='Forecasting Assumptions'!K71 -> 0.02 | P122: ='Forecasting Assumptions'!L71 -> 0.02 | Q122: ='Forecasting Assumptions'!M71 -> 0.02 | R122: ='Forecasting Assumptions'!N71 -> 0.02 | ... T122: ='Forecasting Assumptions'!P71 -> 0.02
B125: Asset Schedule
B127: All figures in USD thousands unless stated | J127: =$J$5 -> 2024 | K127: =$K$5 -> 2025 | L127: =$L$5 -> 2026 | M127: =$M$5 -> 2027 | N127: =$N$5 -> 2028 | O127: =$O$5 -> 2029 | P127: =$P$5 -> 2030 | Q127: =$Q$5 -> 2031 | R127: =$R$5 -> 2032 | S127: =$S$5 -> 2033 | T127: =$T$5 -> 2034
B128: =$B$6 -> Model Running: Base Case Drivers
B130: Capital Expenditure | K130: =K121 -> 24916.788 | L130: =L121 -> 32391.824 | M130: =M121 -> 42109.372 | N130: =N121 -> 54321.09 | O130: =O121 -> 70074.205 | P130: =P121 -> 89204.464 | Q130: =Q121 -> 109364.67 | R130: =R121 -> 128831.58 | ... T130: =T121 -> 157948.04
B132: PROPERTY PLANT & EQUIPMENT
C133: Beginning | K133: =J136 -> 42362 | L133: =K136 -> 42362 | M133: =L136 -> 42362 | N133: =M136 -> 42362 | O133: =N136 -> 42362 | P133: =O136 -> 42362 | Q133: =P136 -> 42362 | R133: =Q136 -> 42362 | ... T133: =S136 -> 42362
C134: Capital Expenditure | K134: =K121 -> 24916.788 | L134: =L121 -> 32391.824 | M134: =M121 -> 42109.372 | N134: =N121 -> 54321.09 | O134: =O121 -> 70074.205 | P134: =P121 -> 89204.464 | Q134: =Q121 -> 109364.67 | R134: =R121 -> 128831.58 | ... T134: =T121 -> 157948.04
C135: Accounting Depreciation | K135: =-K118 -> -24916.788 | L135: =-L118 -> -32391.824 | M135: =-M118 -> -42109.372 | N135: =-N118 -> -54321.09 | O135: =-O118 -> -70074.205 | P135: =-P118 -> -89204.464 | Q135: =-Q118 -> -109364.67 | R135: =-R118 -> -128831.58 | ... T135: =-T118 -> -157948.04
C136: Ending | J136: =BS!C11 -> 42362 | K136: =SUM(K133:K135) -> 42362 | L136: =SUM(L133:L135) -> 42362 | M136: =SUM(M133:M135) -> 42362 | N136: =SUM(N133:N135) -> 42362 | O136: =SUM(O133:O135) -> 42362 | P136: =SUM(P133:P135) -> 42362 | Q136: =SUM(Q133:Q135) -> 42362 | R136: =SUM(R133:R135) -> 42362 | ... T136: =SUM(T133:T135) -> 42362
B139: Income Tax Schedule
B141: All figures in USD thousands unless stated | J141: 2024 | K141: 2025 | L141: 2026 | M141: 2027 | N141: 2028 | O141: 2029 | P141: 2030 | Q141: 2031 | R141: 2032 | S141: 2033 | T141: 2034
B142: =$B$6 -> Model Running: Base Case Drivers
...

Sheet ----->

Sheet IS
A1: (In thousands, except per share data) | B1: Year Ended January 31,
B2: 2022 | C2: 2023 | D2: 2024
A3: Revenue
A4: Subscription | B4: 507375 | C4: 713735 | D4: 904031
A5: Professional services | B5: 43457 | C5: 53180 | D5: 54307
A6: Total revenue | B6: 550832 | C6: 766915 | D6: 958338
A7: Cost of revenue
A8: Subscription | B8: 77460 | C8: 114384 | D8: 134658
A9: Professional services | B9: 39013 | C9: 50901 | D9: 51790
A10: Total cost of revenue | B10: 116473 | C10: 165285 | D10: 186448
A11: Gross profit | B11: 434359 | C11: 601630 | D11: 771890
A12: Operating expenses
A13: Research and development | B13: 165440 | C13: 215205 | D13: 234071
A14: Sales and marketing | B14: 329751 | C14: 479250 | D14: 510576
A15: General and administrative | B15: 109204 | C15: 128811 | D15: 147525
A16: Total operating expenses | B16: 604395 | C16: 823266 | D16: 892172
A17: Loss from operations | B17: -170036 | C17: -221636 | D17: -120282
A18: Interest income | B18: 48 | C18: 7742 | D18: 25641
A19: Other income (expense), net | B19: -813 | C19: 1104 | D19: -1501
A20: Loss before income tax provision | B20: -170801 | C20: -212790 | D20: -96142
A21: Income tax provision | B21: 296 | C21: 2849 | D21: 8489
A22: Net loss | B22: -171097 | C22: -215639 | D22: -104631
A25: SG&A (without D&A) | B25: =B14+B15-B27 -> 417190 | C25: =C14+C15-C27 -> 583205 | D25: =D14+D15-D27 -> 631089
A26: Capex | B26: =(CFS!B28+CFS!B31)*-1 -> 17269 | C26: =(CFS!C28+CFS!C31)*-1 -> 13797 | D26: =(CFS!D28+CFS!D31)*-1 -> 13338
A27: D&A | B27: =CFS!B6 -> 21765 | C27: =CFS!C6 -> 24856 | D27: =CFS!D6 -> 27012
A28: SG&A all without D&A | D28: =D13+D14+D15-D27 -> 865160 | E28: =D28/D6 -> 0.90277126
B30: Hist. | C30: Hist. | D30: Hist.
A31: Metrics | B31: 2022 | C31: 2023 | D31: 2024 | E31: CAGR/Avg
A32: Revenue ($M) | B32: =B6/1000 -> 550.832 | C32: =C6/1000 -> 766.915 | D32: =D6/1000 -> 958.338 | E32: =(D32/B32)^(1/2) - 1 -> 0.31901512
A33: COGS as % of Revenue | B33: =B10/B6 -> 0.21144923 | C33: =C10/C6 -> 0.21551932 | D33: =D10/D6 -> 0.19455349 | E33: =AVERAGE(B33:D33) -> 0.20717401
A34: Gross Margin (%) | B34: =1-B33 -> 0.78855077 | C34: =1-C33 -> 0.78448068 | D34: =1-D33 -> 0.80544651 | E34: =AVERAGE(B34:D34) -> 0.79282599
A35: R&D as % of Revenue | B35: =B13/B6 -> 0.30034566 | C35: =C13/C6 -> 0.28061128 | D35: =D13/D6 -> 0.24424681 | E35: =AVERAGE(B35:D35) -> 0.27506792
A36: SG&A as % of Revenue | B36: =(B14+B15)/B6 -> 0.79689452 | C36: =(C14+C15)/C6 -> 0.79286622 | D36: =(D14+D15)/D6 -> 0.68671074 | E36: =AVERAGE(B36:D36) -> 0.75882383
A37: CapEx as % of Revenue | B37: =B26/B6 -> 0.031350757 | C37: =C26/C6 -> 0.01799026 | D37: =D26/D6 -> 0.013917845 | E37: =AVERAGE(B37:D37) -> 0.021086287
A38: D&A as % of Revenue | B38: =B27/B6 -> 0.039512955 | C38: =C27/C6 -> 0.032410371 | D38: =D27/D6 -> 0.028186298 | E38: =AVERAGE(B38:D38) -> 0.033369875
A39: DSO (Days) | B39: =Model!H97 -> 100.14917 | C39: =Model!I97 -> 94.540718 | D39: =Model!J97 -> 90.916169 | E39: =AVERAGE(B39:D39) -> 95.202021
A40: DPO (Days) | B40: =Model!H98 -> 4.7194629 | C40: =Model!I98 -> 4.6926521 | D40: =Model!J98 -> 5.7496192 | E40: =AVERAGE(B40:D40) -> 5.0539114

Sheet BS
A1: (in thousands, except share data) | B1: January 31,
B2: 2023 | C2: 2024
A3: Assets
A4: Cash and cash equivalents | B4: 223156 | C4: 282094
A5: Short-term investments | B5: 233225 | C5: 346701
A6: Accounts receivable, net | B6: 198643 | C6: 238708
A7: Prepaid expenses and other current assets | B7: 55063 | C7: 64366
A8: Total current assets | B8: 710087 | C8: 931869
A9: Restricted cash | B9: 197 | C9: 19
A10: Deferred commissions | B10: 121785 | C10: 148867
A11: Property and equipment, net | B11: 39395 | C11: 42362
A12: Operating lease right-of-use assets | B12: 54278 | C12: 39480
A13: Intangible assets, net | B13: 39069 | C13: 27960
A14: Goodwill | B14: 142415 | C14: 141477
A15: Other long-term assets | B15: 2983 | C15: 5445
A16: Total assets | B16: 1110209 | C16: 1337479
A17: Liabilities and Shareholders’ Equity
A18: Accounts payable | B18: 2125 | C18: 2937
A19: Accrued compensation and related benefits | B19: 68347 | C19: 77453
A20: Other accrued liabilities | B20: 27437 | C20: 30534
A21: Operating lease liabilities, current | B21: 19220 | C21: 16040
A22: Finance lease liabilities, current | B22: 0 | C22: 216
A23: Deferred revenue, current | B23: 457534 | C23: 568670
A24: Total current liabilities | B24: 574663 | C24: 695850
A25: Operating lease liabilities, non-current | B25: 47564 | C25: 33100
A26: Finance lease liabilities, non-current | B26: 0 | C26: 455
A27: Deferred revenue, non-current | B27: 2195 | C27: 1785
A28: Other long-term liabilities | B28: 129 | C28: 434
A29: Total liabilities | B29: 624551 | C29: 731624
A30: Shareholders’ equity
A31: Additional paid-in capital | B31: 1243730 | C31: 1468805
A32: Accumulated other comprehensive income (loss) | B32: 101 | C32: -146
A33: Accumulated deficit | B33: -758173 | C33: -862804
A34: Total shareholders’ equity | B34: 485658 | C34: 605855
A35: Total liabilities and shareholders’ equity | B35: 1110209 | C35: 1337479

Sheet CFS
A1: (in thousands) | B1: Year Ended January 31,
B2: 2022 | C2: 2023 | D2: 2024
A3: Cash flows from operating activities
A4: Net loss | B4: -171097 | C4: -215639 | D4: -104631
A5: Share-based compensation expense | B5: 114900 | C5: 176555 | D5: 206206
A6: Depreciation and amortization | B6: 21765 | C6: 24856 | D6: 27012
A7: Net amortization of discounts on investments | B7: 0 | C7: -2768 | D7: -12546
A8: Amortization of deferred commission costs | B8: 43680 | C8: 47093 | D8: 53587
A9: Unrealized foreign currency (gain) loss | B9: 1048 | C9: -1198 | D9: 670
A10: Non-cash operating lease costs | B10: 14905 | C10: 18914 | D10: 12012
A11: Impairment of long-lived assets | B11: 0 | C11: 1544 | D11: 1448
A12: Other, net | B12: 0 | C12: -429 | D12: 4042
A13: Accounts receivable | B13: -48575 | C13: -47597 | D13: -43910
A14: Prepaid expenses and other current assets | B14: -19884 | C14: -21437 | D14: -9548
A15: Other long-term assets | B15: 467 | C15: -590 | D15: -3049
... A23: Net cash provided by (used in) operating activities | B23: -3512 | C23: 23588 | D23: 157878
A24: Cash flows from investing activities
A25: Purchases of short-term investments | B25: 0 | C25: -456649 | D25: -513490
A26: Maturities of short-term investments | B26: 0 | C26: 226048 | D26: 413100
A27: Purchases of long-term investments | B27: -1000 | C27: 0 | D27: 0
A28: Purchases of property and equipment | B28: -10563 | C28: -6137 | D28: -2563
A29: Proceeds from sale of property and equipment | B29: 0 | C29: 217 | D29: 42
A30: Proceeds from liquidation of long-term investment | B30: 0 | C30: 622 | D30: 0
A31: Capitalized internal-use software development costs | B31: -6706 | C31: -7660 | D31: -10775
A32: Purchases of intangible assets | B32: -31 | C32: 0 | D32: 0
A33: Payments for business acquisitions, net | B33: 0 | C33: -20342 | D33: 0
A34: Net cash used in investing activities | B34: -18299 | C34: -263901 | D34: -113686
A35: Cash flows from financing activities
A36: Proceeds from exercise of stock options | B36: 19132 | C36: 5633 | D36: 1653
A37: Taxes paid related to net share settlement of RSUs | B37: -6171 | C37: -4177 | D37: -7100
A38: Proceeds from contributions to ESPP | B38: 17380 | C38: 12600 | D38: 20006
A39: Payments on principal of finance leases | B39: 0 | C39: 0 | D39: -34
A40: Net cash provided by financing activities | B40: 30341 | C40: 14056 | D40: 14525
A41: Effect of exchange rate changes on cash | B41: -1197 | C41: 334 | D41: -32
A42: Net increase (decrease) in cash, cash equivalents, and restricted cash | B42: 7332 | C42: -225923 | D42: 58685
A43: Cash, cash equivalents, and restricted cash at beginning of period | B43: 442348 | C43: 449680 | D43: 223757
A44: Cash, cash equivalents, and restricted cash at end of period | B44: 449680 | C44: 223757 | D44: 282442
